pyroll/core/__init__.py
pyroll/core/config.py
pyroll/core/hooks.py
pyroll/core/log.py
pyroll/core/repr.py
pyroll/core/shapes.py
pyroll/core/disk_elements/__init__.py
pyroll/core/disk_elements/disk_element_unit.py
pyroll/core/disk_elements/hookimpls.py
pyroll/core/engine/__init__.py
pyroll/core/engine/engine.py
pyroll/core/engine/hookimpls.py
pyroll/core/grooves/__init__.py
pyroll/core/grooves/base.py
pyroll/core/grooves/equivalent_ripped_groove.py
pyroll/core/grooves/flat.py
pyroll/core/grooves/generic_elongation.py
pyroll/core/grooves/generic_elongation_solvers.py
pyroll/core/grooves/hexagonal.py
pyroll/core/grooves/spline.py
pyroll/core/grooves/boxes/__init__.py
pyroll/core/grooves/boxes/box.py
pyroll/core/grooves/boxes/constricted_box.py
pyroll/core/grooves/boxes/upset_box.py
pyroll/core/grooves/diamonds/__init__.py
pyroll/core/grooves/diamonds/diamond.py
pyroll/core/grooves/diamonds/gothic.py
pyroll/core/grooves/diamonds/square.py
pyroll/core/grooves/ovals/__init__.py
pyroll/core/grooves/ovals/circular_oval.py
pyroll/core/grooves/ovals/constricted_circular_oval.py
pyroll/core/grooves/ovals/constricted_swedish_oval.py
pyroll/core/grooves/ovals/flat_oval.py
pyroll/core/grooves/ovals/oval_3radii.py
pyroll/core/grooves/ovals/oval_3radii_flanked.py
pyroll/core/grooves/ovals/swedish_oval.py
pyroll/core/grooves/ovals/upset_oval.py
pyroll/core/grooves/rounds/__init__.py
pyroll/core/grooves/rounds/false_round.py
pyroll/core/grooves/rounds/round.py
pyroll/core/profile/__init__.py
pyroll/core/profile/hookimpls.py
pyroll/core/profile/profile.py
pyroll/core/roll/__init__.py
pyroll/core/roll/hookimpls.py
pyroll/core/roll/roll.py
pyroll/core/roll_pass/__init__.py
pyroll/core/roll_pass/base.py
pyroll/core/roll_pass/deformation_unit.py
pyroll/core/roll_pass/symmetric_roll_pass.py
pyroll/core/roll_pass/three_roll_pass.py
pyroll/core/roll_pass/two_roll_pass.py
pyroll/core/roll_pass/hookimpls/__init__.py
pyroll/core/roll_pass/hookimpls/base_roll_pass.py
pyroll_core-3.1.1.dist-info/METADATA
pyroll_core-3.1.1.dist-info/WHEEL
pyroll_core-3.1.1.dist-info/licenses/LICENSE
pyroll_core-3.1.1.dist-info/RECORD
