Metadata-Version: 2.4
Name: pyroll-core
Version: 3.1.1
Summary: PyRoll rolling simulation framework - core library.
Project-URL: Homepage, https://pyroll-project.github.io
Project-URL: Repository, https://github.com/pyroll-project/pyroll-core
Project-URL: Documentation, https://pyroll.readthedocs.io/en/latest
Author-email: Max Weiner <max.weiner@imf.tu-freiberg.de>, Christoph Renzing <christoph.renzing@imf.tu-freiberg.de>, Matthias Schmidtchen <matthias.schmidtchen@imf.tu-freiberg.de>, Max Stirl <max.stirl@imf.tu-freiberg.de>
License-Expression: BSD-3-Clause
License-File: LICENSE
Classifier: Development Status :: 5 - Production/Stable
Classifier: Framework :: Hatch
Classifier: Framework :: IPython
Classifier: Framework :: Jupyter
Classifier: Framework :: Pytest
Classifier: Framework :: Sphinx
Classifier: Intended Audience :: Manufacturing
Classifier: Intended Audience :: Science/Research
Classifier: License :: OSI Approved :: BSD License
Classifier: Natural Language :: English
Classifier: Operating System :: OS Independent
Classifier: Programming Language :: Python :: 3
Classifier: Programming Language :: Python :: 3.9
Classifier: Programming Language :: Python :: 3.10
Classifier: Programming Language :: Python :: 3.11
Classifier: Topic :: Scientific/Engineering
Requires-Python: >=3.9
Requires-Dist: numpy~=2.0
Requires-Dist: scipy~=1.13
Requires-Dist: shapely<3.0,>=2.0.6
Provides-Extra: dxf
Requires-Dist: ezdxf-shapely~=1.0; extra == 'dxf'
Provides-Extra: matplotlib
Requires-Dist: matplotlib~=3.7; extra == 'matplotlib'
Provides-Extra: plot
Requires-Dist: matplotlib~=3.7; extra == 'plot'
Provides-Extra: plotly
Requires-Dist: pandas~=2.0; extra == 'plotly'
Requires-Dist: plotly~=5.18; extra == 'plotly'
